tests/__init__.py
tests/test_dns_server.py
tests/test_dns_server_utils.py
tests/test_records.py
windowsdnsserver/__init__.py
windowsdnsserver/command_runner/__init__.py
windowsdnsserver/command_runner/powershell_runner.py
windowsdnsserver/command_runner/runner.py
windowsdnsserver/dns/__init__.py
windowsdnsserver/dns/base.py
windowsdnsserver/dns/dnsserver.py
windowsdnsserver/dns/record.py
windowsdnsserver/exception/__init__.py
windowsdnsserver/exception/exception_common.py
windowsdnsserver/util/__init__.py
windowsdnsserver/util/dns_server_utils.py
windowsdnsserver/util/logger.py
windowsdnsserver_py-0.0.2.dist-info/LICENCE
windowsdnsserver_py-0.0.2.dist-info/METADATA
windowsdnsserver_py-0.0.2.dist-info/WHEEL
windowsdnsserver_py-0.0.2.dist-info/top_level.txt
windowsdnsserver_py-0.0.2.dist-info/RECORD
