Metadata-Version: 2.1
Name: windowsdnsserver-py
Version: 0.0.2
Summary: wrapper Python library for Windows Server DnsServer module
Home-page: https://github.com/bilalekremharmansa/windowsdnsserver-py
Author: Bilal Ekrem Harmansa
Author-email: bilalekremharmansa@gmail.com
License: UNKNOWN
Platform: UNKNOWN
Classifier: Programming Language :: Python :: 3
Classifier: License :: OSI Approved :: MIT License
Classifier: Operating System :: OS Independent
Requires-Python: >=3.5
